{
    "switches": {
        "0": {
            "direction": "unknown",
            "kind": "merge",
            "marks": [
                {
                    "x": 1056,
                    "y": 512
                },
                {
                    "x": 1001,
                    "y": 495
                }
            ],
            "track_ids": []
        }
    },
    "tag groups": {
        "additional_attributes": [],
        "environment": [],
        "light": [],
        "time_of_day": [],
        "track_layout": [],
        "weather": []
    },
    "tracks": {}
}